{
  "description": "",
  "armada_name": "Federation Outpost",
  "group": "federation",
  "head_stats": {
    "attack": 2059772,
    "defense": 2866660,
    "health": 22089365
  },
  "level": 39,
  "rarity": "uncommon",
  "rewards": [
    {
      "type": "Uncommon Armada Credit",
      "max_value": 100490,
      "min_value": 100490,
      "value": 100490
    },
    {
      "type": "Romulan Points",
      "max_value": 5232,
      "min_value": 5232,
      "value": 5232
    },
    {
      "type": "Klingon Points",
      "max_value": 2616,
      "min_value": 2616,
      "value": 2616
    }
  ],
  "stats": {
    "attack": {
      "accuracy": 105556,
      "armor_pierce": 79167,
      "crit_chance": 0.1,
      "crit_damage": 1.5,
      "damage_per_round": 1371772,
      "shield_pierce": 90477
    },
    "defense": {
      "armor": 188493,
      "dodge": 164931,
      "shield_deflect": 219908
    },
    "health": {
      "hull_health": 26231120,
      "shield_health": 17947610
    }
  },
  "systems": [
    {
      "$ref": "systems/groombridge_34_40"
    }
  ],
  "weapons": [
    {
      "firing_pattern": [
        1,
        1,
        1,
        1,
        1,
        1,
        1,
        1,
        1
      ],
      "quantity": 3,
      "weapon_stats": {
        "accuracy": 105556,
        "armor_pierce": 79167,
        "crit_chance": 0.1,
        "crit_damage": 1.5,
        "damage_per_round": 268974,
        "max_damage": 257280,
        "min_damage": 210502,
        "shield_pierce": 90477
      },
      "weapon_type": "energy"
    },
    {
      "firing_pattern": [
        1,
        0,
        1,
        0,
        1,
        0,
        1,
        0,
        1
      ],
      "quantity": 2,
      "weapon_stats": {
        "accuracy": 105556,
        "armor_pierce": 79167,
        "crit_chance": 0.1,
        "crit_damage": 1.5,
        "damage_per_round": 564847,
        "max_damage": 540289,
        "min_damage": 442055,
        "shield_pierce": 90477
      },
      "weapon_type": "kinetic"
    }
  ]
}
