{
  "description": "Bonus base scrapping speed.",
  "img_url": "./assets/apex_chop_shop_outlaw_3_16.png",
  "levels": [
    {
      "bonus": {
        "percentage": true,
        "value": 0.05
      },
      "increased_power": 10500,
      "level": 1,
      "required_by": [],
      "requirements": [
        {
          "name": "Scrapyard",
          "level": 31
        }
      ],
      "research_costs": {
        "materials": [],
        "others": [
          {
            "type": "apex research medal",
            "value": 125
          }
        ],
        "resources": []
      },
      "research_time": 950580
    },
    {
      "bonus": {
        "percentage": true,
        "value": 0.08
      },
      "increased_power": 1250,
      "level": 2,
      "required_by": [],
      "requirements": [
        {
          "name": "Scrapyard",
          "level": 32
        }
      ],
      "research_costs": {
        "materials": [],
        "others": [
          {
            "type": "apex research medal",
            "value": 160
          }
        ],
        "resources": []
      },
      "research_time": 978540
    },
    {
      "bonus": {
        "percentage": true,
        "value": 0.11
      },
      "increased_power": 1250,
      "level": 3,
      "required_by": [],
      "requirements": [
        {
          "name": "Scrapyard",
          "level": 33
        }
      ],
      "research_costs": {
        "materials": [],
        "others": [
          {
            "type": "apex research medal",
            "value": 200
          }
        ],
        "resources": []
      },
      "research_time": 1449420
    },
    {
      "bonus": {
        "percentage": true,
        "value": 0.14
      },
      "increased_power": 1250,
      "level": 4,
      "required_by": [],
      "requirements": [
        {
          "name": "Scrapyard",
          "level": 34
        }
      ],
      "research_costs": {
        "materials": [],
        "others": [
          {
            "type": "apex research medal",
            "value": 250
          }
        ],
        "resources": []
      },
      "research_time": 1937880
    },
    {
      "bonus": {
        "percentage": true,
        "value": 0.17
      },
      "increased_power": 1250,
      "level": 5,
      "required_by": [],
      "requirements": [
        {
          "name": "Scrapyard",
          "level": 35
        }
      ],
      "research_costs": {
        "materials": [],
        "others": [
          {
            "type": "apex research medal",
            "value": 300
          }
        ],
        "resources": []
      },
      "research_time": 2600040
    },
    {
      "bonus": {
        "percentage": true,
        "value": 0.2
      },
      "increased_power": 1500,
      "level": 6,
      "required_by": [],
      "requirements": [],
      "research_costs": {
        "materials": [],
        "others": [
          {
            "type": "apex research medal",
            "value": 370
          }
        ],
        "resources": []
      },
      "research_time": 3499500
    },
    {
      "bonus": {
        "percentage": true,
        "value": 0.23
      },
      "increased_power": 1750,
      "level": 7,
      "required_by": [],
      "requirements": [],
      "research_costs": {
        "materials": [],
        "others": [
          {
            "type": "apex research medal",
            "value": 450
          }
        ],
        "resources": []
      },
      "research_time": 3483960
    },
    {
      "bonus": {
        "percentage": true,
        "value": 0.26
      },
      "increased_power": 1750,
      "level": 8,
      "required_by": [],
      "requirements": [],
      "research_costs": {
        "materials": [],
        "others": [
          {
            "type": "apex research medal",
            "value": 550
          }
        ],
        "resources": []
      },
      "research_time": 5965920
    },
    {
      "bonus": {
        "percentage": true,
        "value": 0.29
      },
      "increased_power": 1500,
      "level": 9,
      "required_by": [],
      "requirements": [],
      "research_costs": {
        "materials": [],
        "others": [
          {
            "type": "apex research medal",
            "value": 650
          }
        ],
        "resources": []
      },
      "research_time": 8058720
    },
    {
      "bonus": {
        "percentage": true,
        "value": 0.32
      },
      "increased_power": 2000,
      "level": 10,
      "required_by": [],
      "requirements": [],
      "research_costs": {
        "materials": [],
        "others": [
          {
            "type": "apex research medal",
            "value": 800
          }
        ],
        "resources": []
      },
      "research_time": 14125380
    },
    {
      "bonus": {
        "percentage": true,
        "value": 0.35
      },
      "increased_power": 2000,
      "level": 11,
      "required_by": [],
      "requirements": [],
      "research_costs": {
        "materials": [],
        "others": [
          {
            "type": "apex research medal",
            "value": 1000
          }
        ],
        "resources": []
      },
      "research_time": 13456140
    },
    {
      "bonus": {
        "percentage": true,
        "value": 0.38
      },
      "increased_power": 2000,
      "level": 12,
      "required_by": [],
      "requirements": [],
      "research_costs": {
        "materials": [],
        "others": [
          {
            "type": "apex research medal",
            "value": 1150
          }
        ],
        "resources": []
      },
      "research_time": 21017460
    },
    {
      "bonus": {
        "percentage": true,
        "value": 0.41
      },
      "increased_power": 2500,
      "level": 13,
      "required_by": [],
      "requirements": [],
      "research_costs": {
        "materials": [],
        "others": [
          {
            "type": "apex research medal",
            "value": 1400
          }
        ],
        "resources": []
      },
      "research_time": 29338800
    },
    {
      "bonus": {
        "percentage": true,
        "value": 0.45
      },
      "increased_power": 2500,
      "level": 14,
      "required_by": [],
      "requirements": [],
      "research_costs": {
        "materials": [],
        "others": [
          {
            "type": "apex research medal",
            "value": 1750
          }
        ],
        "resources": []
      },
      "research_time": 38934120
    },
    {
      "bonus": {
        "percentage": true,
        "value": 0.5
      },
      "increased_power": 2500,
      "level": 15,
      "required_by": [],
      "requirements": [],
      "research_costs": {
        "materials": [],
        "others": [
          {
            "type": "apex research medal",
            "value": 2100
          }
        ],
        "resources": []
      },
      "research_time": 51090420
    }
  ],
  "location": {
    "column": 16,
    "row": 3,
    "tree": "outlaw"
  },
  "research_name": "Apex Chop Shop"
}
