{
  "img_url": "./assets/multi_adaptive_shielding.png",
  "research_name": "Multi-Adaptive Shielding",
  "description": "Increases all Defense stats against ASSIMILATED.",
  "location": {
    "column": 54,
    "row": 3,
    "tree": "combat"
  },
  "levels": [
    {
      "level": 1,
      "increased_power": 110000,
      "bonus": {
        "percentage": true,
        "value": 0.09
      },
      "research_time": 147802,
      "requirements": [
        {
          "name": "Adaptive Weaponry",
          "level": 1
        },
        {
          "name": "R&D Department",
          "level": 48
        }
      ],
      "research_costs": {
        "resources": [
          {
            "type": "dilithium",
            "value": 3065
          }
        ],
        "materials": [
          {
            "value": 20000,
            "grade": 4,
            "rarity": "common",
            "type": "crystal"
          },
          {
            "value": 20000,
            "grade": 4,
            "rarity": "common",
            "type": "gas"
          },
          {
            "value": 20000,
            "grade": 4,
            "rarity": "common",
            "type": "ore"
          }
        ]
      }
    }
  ]
}
