{
  "description": "Increases the mining rate of all grades of crystal, gas, and ore",
  "img_url": "./assets/prime_materials_extractor.png",
  "levels": [
    {
      "bonus": {
        "percentage": true,
        "value": 100
      },
      "increased_power": 23500,
      "level": 1,
      "required_by": [],
      "requirements": [
        {
          "name": "R&D Department",
          "level": 30
        }
      ],
      "research_costs": {
        "materials": [],
        "others": [
          {
            "type": "Away\u00a0Teams\u00a0Particle",
            "value": 500
          },
          {
            "type": "Service\u00a0Award",
            "value": 8800
          }
        ],
        "resources": []
      },
      "research_time": 1852
    }
  ],
  "location": {
    "column": 14,
    "row": 2,
    "tree": "away teams"
  },
  "research_name": "Prime Materials Extractor"
}
