{
  "description": "Bonus base HHP for the Stella.",
  "img_url": "./assets/stella_hull_outlaw_3_11.png",
  "levels": [
    {
      "bonus": {
        "percentage": false,
        "value": 2500.0
      },
      "increased_power": 3400,
      "level": 1,
      "required_by": [],
      "requirements": [
        {
          "name": "Anarchist Weaponry",
          "level": 1
        },
        {
          "name": "Astronautics Studio",
          "level": 27
        }
      ],
      "research_costs": {
        "materials": [],
        "others": [
          {
            "type": "stella particle",
            "value": 200
          },
          {
            "type": "outlaw research credits",
            "value": 200
          },
          {
            "type": "alpha particle",
            "value": 1
          }
        ],
        "resources": [
          {
            "type": "dilithium",
            "value": 36750
          }
        ]
      },
      "research_time": 48480,
      "rewards": [
        {
          "type": "Mission Token",
          "value": 1
        }
      ]
    },
    {
      "bonus": {
        "percentage": false,
        "value": 5000.0
      },
      "increased_power": 200,
      "level": 2,
      "required_by": [],
      "requirements": [
        {
          "name": "Astronautics Studio",
          "level": 27
        }
      ],
      "research_costs": {
        "materials": [],
        "others": [
          {
            "type": "stella particle",
            "value": 260
          },
          {
            "type": "outlaw research credits",
            "value": 300
          }
        ],
        "resources": [
          {
            "type": "dilithium",
            "value": 44064
          }
        ]
      },
      "research_time": 58200
    },
    {
      "bonus": {
        "percentage": false,
        "value": 7500.0
      },
      "increased_power": 200,
      "level": 3,
      "required_by": [],
      "requirements": [
        {
          "name": "Astronautics Studio",
          "level": 28
        }
      ],
      "research_costs": {
        "materials": [],
        "others": [
          {
            "type": "stella particle",
            "value": 400
          },
          {
            "type": "outlaw research credits",
            "value": 400
          }
        ],
        "resources": [
          {
            "type": "dilithium",
            "value": 56000
          }
        ]
      },
      "research_time": 57780
    },
    {
      "bonus": {
        "percentage": false,
        "value": 10000.0
      },
      "increased_power": 400,
      "level": 4,
      "required_by": [],
      "requirements": [
        {
          "name": "Astronautics Studio",
          "level": 28
        }
      ],
      "research_costs": {
        "materials": [],
        "others": [
          {
            "type": "stella particle",
            "value": 530
          },
          {
            "type": "outlaw research credits",
            "value": 500
          }
        ],
        "resources": [
          {
            "type": "dilithium",
            "value": 67230
          }
        ]
      },
      "research_time": 69360
    },
    {
      "bonus": {
        "percentage": false,
        "value": 14000.0
      },
      "increased_power": 500,
      "level": 5,
      "required_by": [],
      "requirements": [
        {
          "name": "Anarchist Weaponry",
          "level": 4
        },
        {
          "name": "Astronautics Studio",
          "level": 30
        }
      ],
      "research_costs": {
        "materials": [],
        "others": [
          {
            "type": "stella particle",
            "value": 790
          },
          {
            "type": "outlaw research credits",
            "value": 1000
          }
        ],
        "resources": [
          {
            "type": "dilithium",
            "value": 134000
          }
        ]
      },
      "research_time": 74100
    },
    {
      "bonus": {
        "percentage": false,
        "value": 18000.0
      },
      "increased_power": 500,
      "level": 6,
      "required_by": [],
      "requirements": [
        {
          "name": "Astronautics Studio",
          "level": 30
        }
      ],
      "research_costs": {
        "materials": [],
        "others": [
          {
            "type": "stella particle",
            "value": 1040
          },
          {
            "type": "outlaw research credits",
            "value": 1200
          }
        ],
        "resources": [
          {
            "type": "dilithium",
            "value": 160920
          }
        ]
      },
      "research_time": 88920
    },
    {
      "bonus": {
        "percentage": false,
        "value": 22000.0
      },
      "increased_power": 550,
      "level": 7,
      "required_by": [],
      "requirements": [
        {
          "name": "Astronautics Studio",
          "level": 32
        }
      ],
      "research_costs": {
        "materials": [],
        "others": [
          {
            "type": "stella particle",
            "value": 9240
          },
          {
            "type": "outlaw research credits",
            "value": 1300
          }
        ],
        "resources": [
          {
            "type": "dilithium",
            "value": 300000
          }
        ]
      },
      "research_time": 97860
    },
    {
      "bonus": {
        "percentage": false,
        "value": 26000.0
      },
      "increased_power": 500,
      "level": 8,
      "required_by": [],
      "requirements": [
        {
          "name": "Anarchist Weaponry",
          "level": 6
        },
        {
          "name": "Astronautics Studio",
          "level": 32
        }
      ],
      "research_costs": {
        "materials": [],
        "others": [
          {
            "type": "stella particle",
            "value": 12200
          },
          {
            "type": "outlaw research credits",
            "value": 1500
          }
        ],
        "resources": [
          {
            "type": "dilithium",
            "value": 359580
          }
        ]
      },
      "research_time": 117420
    },
    {
      "bonus": {
        "percentage": false,
        "value": 31000.0
      },
      "increased_power": 750,
      "level": 9,
      "required_by": [],
      "requirements": [
        {
          "name": "Astronautics Studio",
          "level": 34
        }
      ],
      "research_costs": {
        "materials": [],
        "others": [
          {
            "type": "stella particle",
            "value": 21560
          },
          {
            "type": "outlaw research credits",
            "value": 3300
          }
        ],
        "resources": [
          {
            "type": "dilithium",
            "value": 745000
          }
        ]
      },
      "research_time": 193800
    },
    {
      "bonus": {
        "percentage": false,
        "value": 37000.0
      },
      "increased_power": 1500,
      "level": 10,
      "required_by": [],
      "requirements": [
        {
          "name": "Anarchist Weaponry",
          "level": 10
        },
        {
          "name": "Astronautics Studio",
          "level": 36
        }
      ],
      "research_costs": {
        "materials": [],
        "others": [
          {
            "type": "stella particle",
            "value": 26180
          },
          {
            "type": "outlaw research credits",
            "value": 4500
          }
        ],
        "resources": [
          {
            "type": "dilithium",
            "value": 1660000
          }
        ]
      },
      "research_time": 349980
    },
    {
      "bonus": {
        "percentage": false,
        "value": 43000.0
      },
      "increased_power": 1750,
      "level": 11,
      "required_by": [],
      "requirements": [
        {
          "name": "Crafty Engineering",
          "level": 10
        },
        {
          "name": "Astronautics Studio",
          "level": 38
        }
      ],
      "research_costs": {
        "materials": [],
        "others": [
          {
            "type": "stella particle",
            "value": 52250
          },
          {
            "type": "outlaw research credits",
            "value": 5300
          }
        ],
        "resources": [
          {
            "type": "dilithium",
            "value": 3860000
          }
        ]
      },
      "research_time": 596580
    },
    {
      "bonus": {
        "percentage": false,
        "value": 49000.0
      },
      "increased_power": 1750,
      "level": 12,
      "required_by": [],
      "requirements": [
        {
          "name": "Astronautics Studio",
          "level": 40
        }
      ],
      "research_costs": {
        "materials": [],
        "others": [
          {
            "type": "stella particle",
            "value": 78430
          },
          {
            "type": "outlaw research credits",
            "value": 5400
          }
        ],
        "resources": [
          {
            "type": "dilithium",
            "value": 10400000
          }
        ]
      },
      "research_time": 1412520
    },
    {
      "bonus": {
        "percentage": false,
        "value": 55000.0
      },
      "increased_power": 2000,
      "level": 13,
      "required_by": [],
      "requirements": [
        {
          "name": "Astronautics Studio",
          "level": 42
        }
      ],
      "research_costs": {
        "materials": [],
        "others": [
          {
            "type": "stella particle",
            "value": 104500
          },
          {
            "type": "outlaw research credits",
            "value": 5600
          }
        ],
        "resources": [
          {
            "type": "dilithium",
            "value": 22450000
          }
        ]
      },
      "research_time": 2101740
    },
    {
      "bonus": {
        "percentage": false,
        "value": 60000.0
      },
      "increased_power": 2500,
      "level": 14,
      "required_by": [],
      "requirements": [
        {
          "name": "Astronautics Studio",
          "level": 44
        }
      ],
      "research_costs": {
        "materials": [],
        "others": [
          {
            "type": "stella particle",
            "value": 130900
          },
          {
            "type": "outlaw research credits",
            "value": 5800
          }
        ],
        "resources": [
          {
            "type": "dilithium",
            "value": 49650000
          }
        ]
      },
      "research_time": 3893400
    },
    {
      "bonus": {
        "percentage": false,
        "value": 65000.0
      },
      "increased_power": 2500,
      "level": 15,
      "required_by": [],
      "requirements": [
        {
          "name": "Crafty Engineering",
          "level": 14
        },
        {
          "name": "Astronautics Studio",
          "level": 46
        }
      ],
      "research_costs": {
        "materials": [],
        "others": [
          {
            "type": "stella particle",
            "value": 157300
          },
          {
            "type": "outlaw research credits",
            "value": 6000
          }
        ],
        "resources": [
          {
            "type": "dilithium",
            "value": 98750000
          }
        ]
      },
      "research_time": 6890040
    }
  ],
  "location": {
    "column": 11,
    "row": 3,
    "tree": "outlaw"
  },
  "research_name": "Stella Hull"
}
