{
  "description": "Ahvix is a visitor to our galaxy, albeit an unwilling one. After an incident with her ship, Ahvix found herself stranded here, in the company of Mudd and his crew of Rogues. At first, they were unsure of this unknown alien but Ahvix quickly proved herself as a reliable and skilled officer and became an invaluable asset to the crew.\nWhile she still searches for a way home to this day, Ahvix has found something most unexpected in this strange, new galaxy... Friends.",
  "ability_info": {
    "below_decks_ability": null,
    "captain_maneuver": {
      "name": "Chirurgical Precision",
      "bonus": "When fighting Eclipse hostiles (including Armada Targets), for the first three rounds of combat, Ahvix increases the chances of a Critical Hit by {value}",
      "percentage": true,
      "value": 0.2
    },
    "officer_ability": {
      "name": "Shield Remodulation",
      "bonus": "When fighting Eclipse hostiles (including Armadas), Ahvix has a {value} chance to decrease the Shield Deflection, Armor and Dodge of the opponent by 40% .",
      "percentage": true
    }
  },
  "class": "engineering",
  "faction": "neutral",
  "group": "mudd's company",
  "img_url": "./assets/ahvix.png",
  "officer_name": "Ahvix",
  "ranks": [
    {
      "name": "ENSIGN I",
      "officer_ability_value": 0.25,
      "rank_id": 1,
      "requirements": {
        "badges": 0,
        "credits": 0,
        "others": [],
        "shards": 30,
        "xp": 0
      }
    },
    {
      "name": "LIEUTENANT JG II",
      "officer_ability_value": 0.3,
      "rank_id": 2,
      "requirements": {
        "badges": 0,
        "credits": 0,
        "others": [],
        "shards": 40,
        "xp": 10000
      }
    },
    {
      "name": "LIEUTENANT III",
      "officer_ability_value": 0.35,
      "rank_id": 3,
      "requirements": {
        "badges": 0,
        "credits": 1000,
        "others": [],
        "shards": 85,
        "xp": 100000
      }
    },
    {
      "name": "LT. COMMANDER IV",
      "officer_ability_value": 0.4,
      "rank_id": 4,
      "requirements": {
        "badges": 1,
        "credits": 4000,
        "others": [],
        "shards": 95,
        "xp": 250000
      }
    },
    {
      "name": "COMMANDER V",
      "officer_ability_value": 0.5,
      "rank_id": 5,
      "requirements": {
        "badges": 2,
        "credits": 10000,
        "others": [],
        "shards": 175,
        "xp": 500000
      }
    }
  ],
  "rarity": "rare",
  "synergy": {
    "command": 0.1,
    "engineering": 0.05,
    "science": 0.1
  },
  "traits": [
    {
      "name": "Engineer",
      "levels": [
        {
          "level": 1,
          "trait_xp": 1500
        },
        {
          "level": 2,
          "trait_xp": 2700
        },
        {
          "level": 3,
          "trait_xp": 3800
        }
      ],
      "tier": 1
    },
    {
      "name": "Survivor",
      "levels": [
        {
          "level": 1,
          "trait_xp": 7650
        },
        {
          "level": 2,
          "trait_xp": 6000
        },
        {
          "level": 3,
          "trait_xp": 7000
        },
        {
          "level": 4,
          "trait_xp": 8850
        }
      ],
      "tier": 2
    }
  ]
}
