{
  "description": "",
  "group": "federation",
  "head_stats": {
    "attack": 42428684,
    "defense": 25709015,
    "health": 91086642
  },
  "hostile_name": "Baelosian Spearhead",
  "level": 56,
  "rarity": "common",
  "rewards": [
    {
      "type": "5\u2605 broken interceptor parts",
      "max_value": 604,
      "min_value": 604,
      "value": 604
    },
    {
      "type": "federation points",
      "max_value": 0,
      "min_value": 0,
      "value": 0
    },
    {
      "type": "romulan points",
      "max_value": 39520,
      "min_value": 39520,
      "value": 39520
    },
    {
      "type": "klingon points",
      "max_value": 19760,
      "min_value": 19760,
      "value": 19760
    }
  ],
  "ship_class": "interceptor",
  "stats": {
    "attack": {
      "accuracy": 1374395,
      "armor_pierce": 3360977,
      "crit_chance": 0.1,
      "crit_damage": 1.8,
      "damage_per_round": 31648988,
      "shield_pierce": 654476
    },
    "defense": {
      "armor": 276551,
      "dodge": 4574863,
      "shield_deflect": 290389
    },
    "health": {
      "hull_health": 86749179,
      "shield_health": 95424106
    }
  },
  "systems": [
    {
      "$ref": "systems/x6_094_58"
    },
    {
      "$ref": "systems/tyra_55"
    },
    {
      "$ref": "systems/warren_55"
    },
    {
      "$ref": "systems/garyf_57"
    }
  ],
  "utility": [
    {
      "impulse_speed": 14
    }
  ],
  "weapons": [
    {
      "firing_pattern": [
        3,
        3,
        3,
        3,
        3,
        3,
        3,
        3,
        3,
        3,
        3,
        3,
        3,
        3,
        3
      ],
      "quantity": 1,
      "weapon_stats": {
        "accuracy": 1374395,
        "armor_pierce": 3360977,
        "crit_chance": 0.1,
        "crit_damage": 1.8,
        "damage_per_round": 6880195,
        "max_damage": 2137911,
        "min_damage": 1749205,
        "shield_pierce": 654476
      },
      "weapon_type": "energy"
    },
    {
      "firing_pattern": [
        3,
        0,
        3,
        0,
        3,
        0,
        3,
        0,
        3,
        0,
        3,
        0,
        3,
        0,
        3
      ],
      "quantity": 3,
      "weapon_stats": {
        "accuracy": 1374395,
        "armor_pierce": 3360977,
        "crit_chance": 0.1,
        "crit_damage": 1.8,
        "damage_per_round": 16512528,
        "max_damage": 5131037,
        "min_damage": 4198075,
        "shield_pierce": 654476
      },
      "weapon_type": "kinetic"
    }
  ]
}
