{
  "description": "",
  "group": "federation",
  "head_stats": {
    "attack": 271310,
    "defense": 271875,
    "health": 86625
  },
  "hostile_name": "Federation Patrol",
  "level": 35,
  "rarity": "common",
  "rewards": [],
  "ship_class": "battleship",
  "stats": {
    "attack": {
      "accuracy": 10500,
      "armor_pierce": 7875,
      "crit_chance": 0.1,
      "crit_damage": 1.5,
      "damage_per_round": 162748,
      "shield_pierce": 54000
    },
    "defense": {
      "armor": 36000,
      "dodge": 7875,
      "shield_deflect": 10500
    },
    "health": {
      "hull_health": 85500,
      "shield_health": 87750
    }
  },
  "systems": [
    {
      "$ref": "systems/tau_ceti_34"
    },
    {
      "$ref": "systems/axanar_36"
    }
  ],
  "utility": [
    {
      "impulse_speed": 14
    }
  ],
  "weapons": [
    {
      "firing_pattern": [
        1,
        1,
        1,
        1,
        1,
        1,
        1,
        1,
        1,
        1,
        1,
        1,
        1,
        1,
        1
      ],
      "quantity": 2,
      "weapon_stats": {
        "accuracy": 10500,
        "armor_pierce": 7875,
        "crit_chance": 0.1,
        "crit_damage": 1.5,
        "damage_per_round": 53360,
        "max_damage": 51040,
        "min_damage": 41760,
        "shield_pierce": 54000
      },
      "weapon_type": "energy"
    },
    {
      "firing_pattern": [
        1,
        0,
        1,
        0,
        1,
        0,
        1,
        0,
        1,
        0,
        1,
        0,
        1,
        0,
        1
      ],
      "quantity": 1,
      "weapon_stats": {
        "accuracy": 10500,
        "armor_pierce": 7875,
        "crit_chance": 0.1,
        "crit_damage": 1.5,
        "damage_per_round": 112056,
        "max_damage": 107184,
        "min_damage": 87696,
        "shield_pierce": 54000
      },
      "weapon_type": "kinetic"
    }
  ]
}
