{
  "description": "",
  "group": "klingon",
  "head_stats": {
    "attack": 888396,
    "defense": 717325,
    "health": 2268971
  },
  "hostile_name": "Klingon Fighter",
  "level": 38,
  "rarity": "common",
  "rewards": [],
  "ship_class": "interceptor",
  "stats": {
    "attack": {
      "accuracy": 43420,
      "armor_pierce": 123934,
      "crit_chance": 0.1,
      "crit_damage": 1.8,
      "damage_per_round": 604800,
      "shield_pierce": 21710
    },
    "defense": {
      "armor": 9752,
      "dodge": 123961,
      "shield_deflect": 9752
    },
    "health": {
      "hull_health": 2268971,
      "shield_health": 2268971
    }
  },
  "systems": [
    {
      "$ref": "systems/fafniri_39"
    }
  ],
  "utility": [
    {
      "impulse_speed": 19
    }
  ],
  "weapons": [
    {
      "firing_pattern": [
        3,
        0,
        3,
        0,
        3,
        0,
        3,
        0,
        3,
        0,
        3,
        0,
        3,
        0,
        3
      ],
      "quantity": 2,
      "weapon_stats": {
        "accuracy": 43420,
        "armor_pierce": 123934,
        "crit_chance": 0.1,
        "crit_damage": 1.8,
        "damage_per_round": 426916,
        "max_damage": 132658,
        "min_damage": 108538,
        "shield_pierce": 21710
      },
      "weapon_type": "kinetic"
    },
    {
      "firing_pattern": [
        3,
        3,
        3,
        3,
        3,
        3,
        3,
        3,
        3,
        3,
        3,
        3,
        3,
        3,
        3
      ],
      "quantity": 1,
      "weapon_stats": {
        "accuracy": 43420,
        "armor_pierce": 123934,
        "crit_chance": 0.1,
        "crit_damage": 1.8,
        "damage_per_round": 177883,
        "max_damage": 55274,
        "min_damage": 45225,
        "shield_pierce": 21710
      },
      "weapon_type": "energy"
    }
  ]
}
