{
  "arc": "absolution arc 1",
  "faction": "neutral",
  "mission_name": "Going Back to the Death Place Part 4",
  "mission_type": "auto link / continuation",
  "next_missions": [
    {
      "$ref": "missions/going_back_to_the_death_place_part_5"
    }
  ],
  "objectives": [
    {
      "title": "Defeat Zenith's drone ship.",
      "id": 1,
      "task": {
        "$ref": "systems/dalogn_35",
        "task_title": "Destroy Swarm Elite",
        "task_type": "destroy"
      }
    },
    {
      "title": "Fly back to your station.",
      "id": 2,
      "task": {
        "task_title": "Return your ship to your station.",
        "task_type": "return"
      }
    }
  ],
  "previous_mission": {
    "$ref": "missions/going_back_to_the_death_place_part_3"
  },
  "recommended_level": 40,
  "rewards": {
    "materials": [
      {
        "type": "crystal",
        "grade": 4,
        "rarity": "uncommon",
        "value": 130
      }
    ],
    "others": [],
    "resources": [
      {
        "type": "parsteel",
        "value": 10726000
      },
      {
        "type": "tritanium",
        "value": 1578000
      }
    ]
  },
  "storyline": "Escape Zenith."
}
