{
  "name": "Angosia",
  "capture_nodes": 0,
  "connected_systems": [
    {
      "$ref": "systems/gemet_25",
      "distance": 18,
      "warp": 18
    }
  ],
  "faction": "federation",
  "level": 25,
  "mining": [
    {
      "type": "3\u2605 Raw Gas",
      "amount": 24,
      "grade": 3,
      "mining_per_hour": 300,
      "size": 8500
    }
  ],
  "planets": [
    "Angosia II",
    "Angosia III",
    "Angosia IV",
    "Angosia Prime",
    "Angosia V",
    "Lunar V",
    "Lunar VIII"
  ],
  "scopely_id": 739609161,
  "system_space": "normal",
  "system_type": "terminal",
  "warp": 18
}
