{
  "name": "Esto",
  "capture_nodes": 0,
  "connected_systems": [
    {
      "$ref": "systems/talvath_43",
      "distance": 26,
      "warp": 75
    }
  ],
  "faction": "romulan",
  "hub_details": {
    "hub_number": 8,
    "hub_size": 16
  },
  "level": 43,
  "mining": [
    {
      "type": "Raw Latinum",
      "amount": 12,
      "mining_per_hour": 54,
      "size": 470000
    },
    {
      "type": "Raw Latinum",
      "amount": 12,
      "mining_per_hour": 95,
      "size": 470000
    }
  ],
  "planets": [
    "Anb'bik",
    "Frinia",
    "Grosily",
    "Kanag",
    "Kosonn",
    "Lomnit",
    "Sivetha",
    "Tana",
    "Vin"
  ],
  "scopely_id": 14444521,
  "system_space": "deep",
  "system_type": "terminal",
  "warp": 75
}
