{
  "name": "Lanaj",
  "capture_nodes": 0,
  "connected_systems": [
    {
      "$ref": "systems/nekosa_38",
      "distance": 40,
      "warp": 40
    },
    {
      "$ref": "systems/yadalla_39",
      "distance": 27,
      "warp": 38
    }
  ],
  "faction": "neutral",
  "hub_details": {
    "hub_number": 10,
    "hub_size": 16
  },
  "level": 37,
  "mining": [
    {
      "type": "Parsteel",
      "amount": 5,
      "mining_per_hour": 1200,
      "size": 100000
    }
  ],
  "planets": [
    "Ciluh",
    "Fides",
    "Geeap",
    "Iaeadas",
    "Iajoc",
    "Ieueb",
    "Menukom",
    "Qumeyuw",
    "Sejee",
    "Uavec",
    "Yeuaves"
  ],
  "scopely_id": 1032390550,
  "system_space": "normal",
  "system_type": "route",
  "warp": 38
}
