{
  "name": "Laurgatt",
  "capture_nodes": 0,
  "connected_systems": [
    {
      "$ref": "systems/cymon_2",
      "warp": 2
    },
    {
      "$ref": "systems/falko_2",
      "warp": 2
    },
    {
      "$ref": "systems/hosun_5",
      "warp": 3
    },
    {
      "$ref": "systems/maluria_7",
      "warp": 5
    }
  ],
  "faction": "neutral",
  "hub_details": {
    "hub_number": 8,
    "hub_size": 16
  },
  "level": 4,
  "mining": [
    {
      "type": "parsteel",
      "amount": 4,
      "mining_per_hour": 1200,
      "size": 5000
    }
  ],
  "planets": [
    "Bauau",
    "Cepuh",
    "Garid",
    "Gulukid",
    "Huooweo",
    "Leaipeq",
    "Liail",
    "Ligooud",
    "Tirow",
    "Vocap"
  ],
  "scopely_id": 74130,
  "system_space": "normal",
  "system_type": "hub",
  "warp": 3
}
