{
  "name": "Naalur",
  "capture_nodes": 0,
  "connected_systems": [
    {
      "$ref": "systems/alycen_44",
      "warp": 110
    },
    {
      "$ref": "systems/draomn_44",
      "warp": 110
    },
    {
      "$ref": "systems/veisa_46",
      "warp": 120
    }
  ],
  "faction": "romulan",
  "level": 44,
  "mining": [
    {
      "type": "tritanium",
      "amount": 6,
      "mining_per_hour": 320,
      "size": 1000000
    }
  ],
  "planets": [
    "Stavihx",
    "Vleh"
  ],
  "scopely_id": 708767738,
  "system_space": "deep",
  "system_type": "hub",
  "warp": 110
}
